{"mixed5b": [{"channel": 313, "count": 154, "layer": "mixed5b", "pagerank": 0.0006609269076338533, "prev_channels": [{"prev_channel": 249, "inf": 286}], "attr_channels": [{"prev_channel": "776", "inf": 925}, {"prev_channel": "132", "inf": 531}, {"prev_channel": "803", "inf": 493}]}, {"channel": 385, "count": 83, "layer": "mixed5b", "pagerank": 0.0004782006234918016, "prev_channels": [{"prev_channel": 249, "inf": 667}, {"prev_channel": 0, "inf": 422}, {"prev_channel": 732, "inf": 811}, {"prev_channel": 190, "inf": 642}, {"prev_channel": 647, "inf": 233}, {"prev_channel": 86, "inf": 332}, {"prev_channel": 391, "inf": 422}], "attr_channels": [{"prev_channel": "37", "inf": 1248}, {"prev_channel": "111", "inf": 895}, {"prev_channel": "23", "inf": 667}]}, {"channel": 520, "count": 295, "layer": "mixed5b", "pagerank": 0.0013412873057182004, "prev_channels": [{"prev_channel": 249, "inf": 667}, {"prev_channel": 0, "inf": 1018}, {"prev_channel": 732, "inf": 783}, {"prev_channel": 190, "inf": 642}, {"prev_channel": 647, "inf": 139}, {"prev_channel": 86, "inf": 332}, {"prev_channel": 391, "inf": 201}], "attr_channels": [{"prev_channel": "37", "inf": 1262}, {"prev_channel": "23", "inf": 1161}, {"prev_channel": "95", "inf": 1018}]}, {"channel": 528, "count": 77, "layer": "mixed5b", "pagerank": 0.000452632651699807, "prev_channels": [{"prev_channel": 249, "inf": 667}, {"prev_channel": 0, "inf": 482}, {"prev_channel": 732, "inf": 783}, {"prev_channel": 190, "inf": 414}, {"prev_channel": 647, "inf": 407}, {"prev_channel": 86, "inf": 485}, {"prev_channel": 391, "inf": 459}], "attr_channels": [{"prev_channel": "37", "inf": 1244}, {"prev_channel": "172", "inf": 656}, {"prev_channel": "181", "inf": 544}]}, {"channel": 566, "count": 77, "layer": "mixed5b", "pagerank": 0.00044856783526363915, "prev_channels": [{"prev_channel": 249, "inf": 667}, {"prev_channel": 0, "inf": 372}, {"prev_channel": 732, "inf": 783}, {"prev_channel": 190, "inf": 642}, {"prev_channel": 647, "inf": 141}, {"prev_channel": 86, "inf": 332}, {"prev_channel": 391, "inf": 459}], "attr_channels": [{"prev_channel": "172", "inf": 938}, {"prev_channel": "37", "inf": 857}, {"prev_channel": "157", "inf": 730}]}, {"channel": 627, "count": 59, "layer": "mixed5b", "pagerank": 0.0003784654210313717, "prev_channels": [{"prev_channel": 249, "inf": 667}, {"prev_channel": 732, "inf": 811}, {"prev_channel": 190, "inf": 376}, {"prev_channel": 647, "inf": 238}, {"prev_channel": 86, "inf": 682}, {"prev_channel": 391, "inf": 682}], "attr_channels": [{"prev_channel": "37", "inf": 1087}, {"prev_channel": "111", "inf": 1015}, {"prev_channel": "187", "inf": 682}]}, {"channel": 656, "count": 70, "layer": "mixed5b", "pagerank": 0.0004094730144159574, "prev_channels": [{"prev_channel": 249, "inf": 667}, {"prev_channel": 0, "inf": 1070}, {"prev_channel": 732, "inf": 783}, {"prev_channel": 190, "inf": 444}, {"prev_channel": 86, "inf": 172}, {"prev_channel": 391, "inf": 459}], "attr_channels": [{"prev_channel": "37", "inf": 1270}, {"prev_channel": "95", "inf": 1098}, {"prev_channel": "172", "inf": 827}]}, {"channel": 763, "count": 65, "layer": "mixed5b", "pagerank": 0.0003953898762946217, "prev_channels": [{"prev_channel": 249, "inf": 626}, {"prev_channel": 0, "inf": 802}, {"prev_channel": 732, "inf": 811}, {"prev_channel": 190, "inf": 444}, {"prev_channel": 86, "inf": 238}, {"prev_channel": 391, "inf": 184}], "attr_channels": [{"prev_channel": "111", "inf": 1119}, {"prev_channel": "95", "inf": 802}, {"prev_channel": "0", "inf": 731}]}, {"channel": 820, "count": 78, "layer": "mixed5b", "pagerank": 0.0004412906486567208, "prev_channels": [{"prev_channel": 249, "inf": 616}, {"prev_channel": 0, "inf": 591}, {"prev_channel": 732, "inf": 711}, {"prev_channel": 190, "inf": 311}, {"prev_channel": 647, "inf": 387}, {"prev_channel": 86, "inf": 368}, {"prev_channel": 391, "inf": 158}], "attr_channels": [{"prev_channel": "20", "inf": 1224}, {"prev_channel": "19", "inf": 1097}, {"prev_channel": "44", "inf": 1013}]}, {"channel": 823, "count": 82, "layer": "mixed5b", "pagerank": 0.000463074132129716, "prev_channels": [{"prev_channel": 249, "inf": 310}, {"prev_channel": 0, "inf": 638}, {"prev_channel": 732, "inf": 384}, {"prev_channel": 190, "inf": 311}, {"prev_channel": 86, "inf": 462}, {"prev_channel": 391, "inf": 158}], "attr_channels": [{"prev_channel": "19", "inf": 1259}, {"prev_channel": "13", "inf": 1029}, {"prev_channel": "11", "inf": 929}]}, {"channel": 851, "count": 67, "layer": "mixed5b", "pagerank": 0.00040728564881478224, "prev_channels": [{"prev_channel": 249, "inf": 468}, {"prev_channel": 0, "inf": 698}, {"prev_channel": 732, "inf": 384}, {"prev_channel": 190, "inf": 311}, {"prev_channel": 647, "inf": 698}, {"prev_channel": 86, "inf": 368}, {"prev_channel": 391, "inf": 158}], "attr_channels": [{"prev_channel": "19", "inf": 1220}, {"prev_channel": "14", "inf": 1192}, {"prev_channel": "31", "inf": 1077}]}, {"channel": 854, "count": 69, "layer": "mixed5b", "pagerank": 0.00040430360416603774, "prev_channels": [{"prev_channel": 249, "inf": 581}, {"prev_channel": 0, "inf": 719}, {"prev_channel": 732, "inf": 418}, {"prev_channel": 190, "inf": 337}, {"prev_channel": 647, "inf": 138}, {"prev_channel": 391, "inf": 380}], "attr_channels": [{"prev_channel": "19", "inf": 1250}, {"prev_channel": "13", "inf": 1189}, {"prev_channel": "14", "inf": 779}]}, {"channel": 885, "count": 133, "layer": "mixed5b", "pagerank": 0.0006838438004883158, "prev_channels": [{"prev_channel": 249, "inf": 851}, {"prev_channel": 0, "inf": 750}, {"prev_channel": 732, "inf": 563}, {"prev_channel": 190, "inf": 298}, {"prev_channel": 647, "inf": 764}, {"prev_channel": 86, "inf": 1185}], "attr_channels": [{"prev_channel": "30", "inf": 1247}, {"prev_channel": "22", "inf": 1109}, {"prev_channel": "4", "inf": 1022}]}, {"channel": 229, "count": 111, "layer": "mixed5b", "pagerank": 0.0004842651184036065, "prev_channels": [{"prev_channel": 0, "inf": 481}, {"prev_channel": 391, "inf": 1}], "attr_channels": [{"prev_channel": "811", "inf": 882}, {"prev_channel": "43", "inf": 721}, {"prev_channel": "0", "inf": 481}]}, {"channel": 243, "count": 90, "layer": "mixed5b", "pagerank": 0.0003988259103513484, "prev_channels": [{"prev_channel": 732, "inf": 442}, {"prev_channel": 190, "inf": 2}, {"prev_channel": 86, "inf": 488}, {"prev_channel": 391, "inf": 262}], "attr_channels": [{"prev_channel": "811", "inf": 868}, {"prev_channel": "792", "inf": 625}, {"prev_channel": "544", "inf": 570}]}, {"channel": 338, "count": 117, "layer": "mixed5b", "pagerank": 0.0005092136928107539, "prev_channels": [{"prev_channel": 732, "inf": 389}, {"prev_channel": 391, "inf": 608}], "attr_channels": [{"prev_channel": "121", "inf": 837}, {"prev_channel": "197", "inf": 609}, {"prev_channel": "391", "inf": 608}]}], "mixed5a": [{"channel": 249, "count": 161, "layer": "mixed5a", "pagerank": 0.0016214015014404438, "prev_channels": [{"prev_channel": 759, "inf": 532}], "attr_channels": [{"prev_channel": "113", "inf": 1081}, {"prev_channel": "721", "inf": 996}, {"prev_channel": "23", "inf": 648}]}, {"channel": 0, "count": 162, "layer": "mixed5a", "pagerank": 0.0016449079366801544, "prev_channels": [{"prev_channel": 713, "inf": 1112}, {"prev_channel": 597, "inf": 299}, {"prev_channel": 734, "inf": 4}], "attr_channels": [{"prev_channel": "713", "inf": 1112}, {"prev_channel": "698", "inf": 637}, {"prev_channel": "541", "inf": 597}]}, {"channel": 732, "count": 215, "layer": "mixed5a", "pagerank": 0.00211859872934872, "prev_channels": [{"prev_channel": 713, "inf": 1129}, {"prev_channel": 597, "inf": 111}, {"prev_channel": 734, "inf": 124}], "attr_channels": [{"prev_channel": "713", "inf": 1129}, {"prev_channel": "537", "inf": 615}, {"prev_channel": "321", "inf": 608}]}, {"channel": 190, "count": 320, "layer": "mixed5a", "pagerank": 0.0018534419211576158, "prev_channels": [{"prev_channel": 759, "inf": 631}, {"prev_channel": 734, "inf": 1153}, {"prev_channel": 713, "inf": 512}], "attr_channels": [{"prev_channel": "734", "inf": 1153}, {"prev_channel": "759", "inf": 631}, {"prev_channel": "786", "inf": 591}]}, {"channel": 647, "count": 721, "layer": "mixed5a", "pagerank": 0.002447743962808587, "prev_channels": [{"prev_channel": 713, "inf": 1179}, {"prev_channel": 734, "inf": 1086}, {"prev_channel": 597, "inf": 984}, {"prev_channel": 759, "inf": 781}], "attr_channels": [{"prev_channel": "30", "inf": 1296}, {"prev_channel": "0", "inf": 1226}, {"prev_channel": "3", "inf": 1150}]}, {"channel": 86, "count": 123, "layer": "mixed5a", "pagerank": 0.0016612102428292998, "prev_channels": [{"prev_channel": 759, "inf": 690}, {"prev_channel": 713, "inf": 1168}], "attr_channels": [{"prev_channel": "713", "inf": 1168}, {"prev_channel": "763", "inf": 923}, {"prev_channel": "782", "inf": 841}]}, {"channel": 391, "count": 312, "layer": "mixed5a", "pagerank": 0.0017354713319937408, "prev_channels": [{"prev_channel": 713, "inf": 862}, {"prev_channel": 734, "inf": 787}, {"prev_channel": 597, "inf": 708}, {"prev_channel": 759, "inf": 671}], "attr_channels": [{"prev_channel": "59", "inf": 1295}, {"prev_channel": "149", "inf": 787}, {"prev_channel": "49", "inf": 604}]}], "mixed4e": [{"channel": 713, "count": 474, "layer": "mixed4e", "pagerank": 0.00239645477865044, "prev_channels": [{"prev_channel": 431, "inf": 1186}, {"prev_channel": 428, "inf": 169}, {"prev_channel": 501, "inf": 418}, {"prev_channel": 446, "inf": 495}], "attr_channels": [{"prev_channel": "431", "inf": 1186}, {"prev_channel": "43", "inf": 997}, {"prev_channel": "422", "inf": 674}]}, {"channel": 597, "count": 273, "layer": "mixed4e", "pagerank": 0.0015776793933545965, "prev_channels": [{"prev_channel": 428, "inf": 1176}, {"prev_channel": 431, "inf": 686}, {"prev_channel": 446, "inf": 634}, {"prev_channel": 225, "inf": 213}], "attr_channels": [{"prev_channel": "13", "inf": 1300}, {"prev_channel": "22", "inf": 1300}, {"prev_channel": "1", "inf": 985}]}, {"channel": 734, "count": 576, "layer": "mixed4e", "pagerank": 0.0025410686912655245, "prev_channels": [{"prev_channel": 428, "inf": 614}, {"prev_channel": 225, "inf": 1076}, {"prev_channel": 431, "inf": 28}], "attr_channels": [{"prev_channel": "383", "inf": 1220}, {"prev_channel": "225", "inf": 1076}, {"prev_channel": "28", "inf": 928}]}, {"channel": 759, "count": 525, "layer": "mixed4e", "pagerank": 0.002324409798571397, "prev_channels": [{"prev_channel": 431, "inf": 565}, {"prev_channel": 428, "inf": 27}], "attr_channels": [{"prev_channel": "477", "inf": 987}, {"prev_channel": "217", "inf": 933}, {"prev_channel": "486", "inf": 638}]}], "mixed4d": [{"channel": 225, "count": 312, "layer": "mixed4d", "pagerank": 0.0011538292652338244, "prev_channels": [{"prev_channel": 172, "inf": 884}, {"prev_channel": 409, "inf": 602}, {"prev_channel": 264, "inf": 514}, {"prev_channel": 325, "inf": 352}, {"prev_channel": 414, "inf": 350}], "attr_channels": [{"prev_channel": "12", "inf": 1030}, {"prev_channel": "137", "inf": 884}, {"prev_channel": "124", "inf": 757}]}, {"channel": 446, "count": 240, "layer": "mixed4d", "pagerank": 0.000960912467662495, "prev_channels": [{"prev_channel": 172, "inf": 659}, {"prev_channel": 414, "inf": 571}, {"prev_channel": 409, "inf": 540}], "attr_channels": [{"prev_channel": "15", "inf": 1263}, {"prev_channel": "27", "inf": 1235}, {"prev_channel": "4", "inf": 1186}]}, {"channel": 428, "count": 610, "layer": "mixed4d", "pagerank": 0.002075600025244119, "prev_channels": [{"prev_channel": 415, "inf": 1063}, {"prev_channel": 172, "inf": 1005}, {"prev_channel": 325, "inf": 980}, {"prev_channel": 414, "inf": 913}, {"prev_channel": 409, "inf": 667}, {"prev_channel": 264, "inf": 627}], "attr_channels": [{"prev_channel": "6", "inf": 1290}, {"prev_channel": "2", "inf": 1171}, {"prev_channel": "15", "inf": 1153}]}, {"channel": 431, "count": 726, "layer": "mixed4d", "pagerank": 0.0025759801325856047, "prev_channels": [{"prev_channel": 415, "inf": 1063}, {"prev_channel": 325, "inf": 908}, {"prev_channel": 172, "inf": 847}, {"prev_channel": 409, "inf": 803}], "attr_channels": [{"prev_channel": "15", "inf": 1298}, {"prev_channel": "0", "inf": 1294}, {"prev_channel": "12", "inf": 1273}]}, {"channel": 501, "count": 221, "layer": "mixed4d", "pagerank": 0.000920769901518491, "prev_channels": [{"prev_channel": 264, "inf": 231}], "attr_channels": [{"prev_channel": "246", "inf": 744}, {"prev_channel": "245", "inf": 636}, {"prev_channel": "336", "inf": 630}]}], "mixed4c": [{"channel": 409, "count": 277, "layer": "mixed4c", "pagerank": 0.0012552792392465195, "prev_channels": [{"prev_channel": 439, "inf": 1249}, {"prev_channel": 408, "inf": 1127}, {"prev_channel": 396, "inf": 958}, {"prev_channel": 418, "inf": 815}, {"prev_channel": 436, "inf": 450}], "attr_channels": [{"prev_channel": "23", "inf": 1300}, {"prev_channel": "8", "inf": 1293}, {"prev_channel": "1", "inf": 1241}]}, {"channel": 264, "count": 288, "layer": "mixed4c", "pagerank": 0.0011328343521712948, "prev_channels": [{"prev_channel": 396, "inf": 715}, {"prev_channel": 418, "inf": 671}, {"prev_channel": 439, "inf": 460}, {"prev_channel": 408, "inf": 279}], "attr_channels": [{"prev_channel": "14", "inf": 1230}, {"prev_channel": "38", "inf": 715}, {"prev_channel": "74", "inf": 699}]}, {"channel": 172, "count": 440, "layer": "mixed4c", "pagerank": 0.0016168944294257573, "prev_channels": [{"prev_channel": 396, "inf": 837}, {"prev_channel": 418, "inf": 534}, {"prev_channel": 439, "inf": 208}], "attr_channels": [{"prev_channel": "43", "inf": 1228}, {"prev_channel": "95", "inf": 1176}, {"prev_channel": "21", "inf": 837}]}, {"channel": 414, "count": 555, "layer": "mixed4c", "pagerank": 0.0017091100193506038, "prev_channels": [{"prev_channel": 436, "inf": 1217}, {"prev_channel": 396, "inf": 958}, {"prev_channel": 439, "inf": 826}, {"prev_channel": 418, "inf": 815}, {"prev_channel": 408, "inf": 451}], "attr_channels": [{"prev_channel": "10", "inf": 1300}, {"prev_channel": "8", "inf": 1053}, {"prev_channel": "3", "inf": 1051}]}, {"channel": 415, "count": 466, "layer": "mixed4c", "pagerank": 0.001441147797803246, "prev_channels": [{"prev_channel": 408, "inf": 1196}, {"prev_channel": 436, "inf": 958}, {"prev_channel": 396, "inf": 958}, {"prev_channel": 418, "inf": 815}, {"prev_channel": 439, "inf": 345}], "attr_channels": [{"prev_channel": "8", "inf": 1300}, {"prev_channel": "5", "inf": 1196}, {"prev_channel": "19", "inf": 991}]}, {"channel": 325, "count": 287, "layer": "mixed4c", "pagerank": 0.0012808812755970823, "prev_channels": [{"prev_channel": 396, "inf": 946}, {"prev_channel": 408, "inf": 561}, {"prev_channel": 439, "inf": 326}, {"prev_channel": 418, "inf": 233}], "attr_channels": [{"prev_channel": "68", "inf": 1238}, {"prev_channel": "43", "inf": 1212}, {"prev_channel": "42", "inf": 1044}]}], "mixed4b": [{"channel": 396, "count": 262, "layer": "mixed4b", "pagerank": 0.0016102502908938085, "prev_channels": [{"prev_channel": 374, "inf": 1228}, {"prev_channel": 255, "inf": 1144}, {"prev_channel": 199, "inf": 358}, {"prev_channel": 264, "inf": 285}, {"prev_channel": 267, "inf": 215}], "attr_channels": [{"prev_channel": "0", "inf": 1300}, {"prev_channel": "6", "inf": 1277}, {"prev_channel": "2", "inf": 1271}]}, {"channel": 418, "count": 484, "layer": "mixed4b", "pagerank": 0.0020833941889272156, "prev_channels": [{"prev_channel": 374, "inf": 1228}, {"prev_channel": 255, "inf": 1144}, {"prev_channel": 199, "inf": 828}, {"prev_channel": 267, "inf": 538}], "attr_channels": [{"prev_channel": "2", "inf": 1259}, {"prev_channel": "6", "inf": 1259}, {"prev_channel": "19", "inf": 1016}]}, {"channel": 408, "count": 510, "layer": "mixed4b", "pagerank": 0.0021740825971447754, "prev_channels": [{"prev_channel": 374, "inf": 919}, {"prev_channel": 199, "inf": 828}, {"prev_channel": 255, "inf": 599}, {"prev_channel": 267, "inf": 538}], "attr_channels": [{"prev_channel": "15", "inf": 1292}, {"prev_channel": "4", "inf": 1251}, {"prev_channel": "19", "inf": 1240}]}, {"channel": 436, "count": 400, "layer": "mixed4b", "pagerank": 0.0017734035172876788, "prev_channels": [{"prev_channel": 374, "inf": 988}, {"prev_channel": 255, "inf": 988}, {"prev_channel": 199, "inf": 662}, {"prev_channel": 267, "inf": 538}], "attr_channels": [{"prev_channel": "23", "inf": 1292}, {"prev_channel": "2", "inf": 1145}, {"prev_channel": "6", "inf": 988}]}, {"channel": 439, "count": 400, "layer": "mixed4b", "pagerank": 0.0017408160750498906, "prev_channels": [{"prev_channel": 374, "inf": 1228}, {"prev_channel": 255, "inf": 1144}, {"prev_channel": 199, "inf": 828}, {"prev_channel": 267, "inf": 538}, {"prev_channel": 264, "inf": 157}], "attr_channels": [{"prev_channel": "2", "inf": 1271}, {"prev_channel": "6", "inf": 1230}, {"prev_channel": "19", "inf": 1123}]}], "mixed4a": [{"channel": 140, "count": 96, "layer": "mixed4a", "pagerank": 0.0012062077275296075, "prev_channels": [], "attr_channels": [{"prev_channel": "204", "inf": 1300}, {"prev_channel": "412", "inf": 1300}, {"prev_channel": "390", "inf": 1300}]}, {"channel": 199, "count": 368, "layer": "mixed4a", "pagerank": 0.001679510201659591, "prev_channels": [{"prev_channel": 389, "inf": 658}, {"prev_channel": 152, "inf": 594}], "attr_channels": [{"prev_channel": "49", "inf": 1022}, {"prev_channel": "72", "inf": 860}, {"prev_channel": "68", "inf": 749}]}, {"channel": 255, "count": 237, "layer": "mixed4a", "pagerank": 0.0012794456535963011, "prev_channels": [{"prev_channel": 152, "inf": 649}, {"prev_channel": 389, "inf": 227}], "attr_channels": [{"prev_channel": "5", "inf": 1297}, {"prev_channel": "10", "inf": 1259}, {"prev_channel": "93", "inf": 897}]}, {"channel": 374, "count": 242, "layer": "mixed4a", "pagerank": 0.0012819812283647, "prev_channels": [{"prev_channel": 368, "inf": 772}, {"prev_channel": 152, "inf": 637}], "attr_channels": [{"prev_channel": "10", "inf": 1164}, {"prev_channel": "92", "inf": 1072}, {"prev_channel": "1", "inf": 1069}]}, {"channel": 267, "count": 609, "layer": "mixed4a", "pagerank": 0.002149107539437992, "prev_channels": [{"prev_channel": 389, "inf": 922}, {"prev_channel": 368, "inf": 535}, {"prev_channel": 379, "inf": 285}], "attr_channels": [{"prev_channel": "78", "inf": 1234}, {"prev_channel": "6", "inf": 922}, {"prev_channel": "79", "inf": 738}]}, {"channel": 264, "count": 302, "layer": "mixed4a", "pagerank": 0.0014559245775327648, "prev_channels": [{"prev_channel": 389, "inf": 1166}, {"prev_channel": 379, "inf": 285}], "attr_channels": [{"prev_channel": "6", "inf": 1259}, {"prev_channel": "37", "inf": 1258}, {"prev_channel": "29", "inf": 618}]}], "mixed3b": [{"channel": 343, "count": 275, "layer": "mixed3b", "pagerank": 0.0012763553140634036, "prev_channels": [{"prev_channel": 101, "inf": 1040}], "attr_channels": [{"prev_channel": "23", "inf": 1299}, {"prev_channel": "27", "inf": 1298}, {"prev_channel": "17", "inf": 1297}]}, {"channel": 389, "count": 205, "layer": "mixed3b", "pagerank": 0.0012665846517386278, "prev_channels": [{"prev_channel": 101, "inf": 623}], "attr_channels": [{"prev_channel": "14", "inf": 1299}, {"prev_channel": "27", "inf": 1291}, {"prev_channel": "19", "inf": 1116}]}, {"channel": 152, "count": 383, "layer": "mixed3b", "pagerank": 0.0016643421667818844, "prev_channels": [{"prev_channel": 76, "inf": 1233}], "attr_channels": [{"prev_channel": "102", "inf": 1279}, {"prev_channel": "15", "inf": 1272}, {"prev_channel": "48", "inf": 1270}]}, {"channel": 368, "count": 187, "layer": "mixed3b", "pagerank": 0.0011862005617140666, "prev_channels": [{"prev_channel": 134, "inf": 1296}, {"prev_channel": 101, "inf": 895}], "attr_channels": [{"prev_channel": "4", "inf": 1300}, {"prev_channel": "14", "inf": 1232}, {"prev_channel": "24", "inf": 1028}]}, {"channel": 374, "count": 159, "layer": "mixed3b", "pagerank": 0.001119159025243827, "prev_channels": [{"prev_channel": 101, "inf": 859}], "attr_channels": [{"prev_channel": "15", "inf": 1115}, {"prev_channel": "23", "inf": 906}, {"prev_channel": "3", "inf": 738}]}, {"channel": 349, "count": 282, "layer": "mixed3b", "pagerank": 0.001337780569354447, "prev_channels": [{"prev_channel": 101, "inf": 1288}, {"prev_channel": 134, "inf": 832}], "attr_channels": [{"prev_channel": "21", "inf": 1300}, {"prev_channel": "24", "inf": 1150}, {"prev_channel": "0", "inf": 1115}]}, {"channel": 379, "count": 262, "layer": "mixed3b", "pagerank": 0.0012590072414193838, "prev_channels": [{"prev_channel": 134, "inf": 1200}], "attr_channels": [{"prev_channel": "8", "inf": 1300}, {"prev_channel": "19", "inf": 1300}, {"prev_channel": "7", "inf": 1299}]}], "mixed3a": [{"channel": 76, "count": 318, "layer": "mixed3a", "pagerank": 0.001606399134540096, "prev_channels": [], "attr_channels": []}, {"channel": 101, "count": 294, "layer": "mixed3a", "pagerank": 0.0020882246804800105, "prev_channels": [], "attr_channels": []}, {"channel": 134, "count": 374, "layer": "mixed3a", "pagerank": 0.0020219643810989747, "prev_channels": [], "attr_channels": []}]}