{"mixed5b": [{"channel": 768, "count": 90, "layer": "mixed5b", "pagerank": 0.0006165880627528482, "prev_channels": [{"prev_channel": 388, "inf": 828}, {"prev_channel": 806, "inf": 186}, {"prev_channel": 754, "inf": 256}, {"prev_channel": 239, "inf": 474}, {"prev_channel": 155, "inf": 256}], "attr_channels": [{"prev_channel": "7", "inf": 1084}, {"prev_channel": "41", "inf": 1049}, {"prev_channel": "37", "inf": 984}]}, {"channel": 770, "count": 171, "layer": "mixed5b", "pagerank": 0.0010471358157992847, "prev_channels": [{"prev_channel": 388, "inf": 1027}, {"prev_channel": 806, "inf": 144}, {"prev_channel": 754, "inf": 618}, {"prev_channel": 239, "inf": 474}, {"prev_channel": 155, "inf": 572}], "attr_channels": [{"prev_channel": "40", "inf": 1242}, {"prev_channel": "20", "inf": 1097}, {"prev_channel": "37", "inf": 1038}]}, {"channel": 794, "count": 85, "layer": "mixed5b", "pagerank": 0.0005984295351339161, "prev_channels": [{"prev_channel": 388, "inf": 687}, {"prev_channel": 754, "inf": 618}, {"prev_channel": 239, "inf": 251}, {"prev_channel": 155, "inf": 210}], "attr_channels": [{"prev_channel": "20", "inf": 1213}, {"prev_channel": "41", "inf": 1140}, {"prev_channel": "31", "inf": 780}]}, {"channel": 832, "count": 98, "layer": "mixed5b", "pagerank": 0.0006635236132895175, "prev_channels": [{"prev_channel": 388, "inf": 539}, {"prev_channel": 806, "inf": 420}, {"prev_channel": 754, "inf": 200}, {"prev_channel": 239, "inf": 474}, {"prev_channel": 155, "inf": 175}], "attr_channels": [{"prev_channel": "11", "inf": 1187}, {"prev_channel": "47", "inf": 1056}, {"prev_channel": "37", "inf": 870}]}, {"channel": 834, "count": 228, "layer": "mixed5b", "pagerank": 0.001335925282613302, "prev_channels": [{"prev_channel": 388, "inf": 491}, {"prev_channel": 806, "inf": 567}, {"prev_channel": 754, "inf": 446}, {"prev_channel": 239, "inf": 474}, {"prev_channel": 155, "inf": 257}], "attr_channels": [{"prev_channel": "37", "inf": 1173}, {"prev_channel": "45", "inf": 1156}, {"prev_channel": "11", "inf": 1135}]}, {"channel": 852, "count": 95, "layer": "mixed5b", "pagerank": 0.0006398202867055026, "prev_channels": [{"prev_channel": 388, "inf": 351}, {"prev_channel": 806, "inf": 562}, {"prev_channel": 754, "inf": 200}, {"prev_channel": 239, "inf": 474}, {"prev_channel": 155, "inf": 137}], "attr_channels": [{"prev_channel": "47", "inf": 1235}, {"prev_channel": "41", "inf": 1144}, {"prev_channel": "37", "inf": 993}]}, {"channel": 886, "count": 105, "layer": "mixed5b", "pagerank": 0.0007093808654878067, "prev_channels": [{"prev_channel": 388, "inf": 631}, {"prev_channel": 806, "inf": 340}, {"prev_channel": 754, "inf": 340}, {"prev_channel": 239, "inf": 474}, {"prev_channel": 155, "inf": 631}], "attr_channels": [{"prev_channel": "45", "inf": 1269}, {"prev_channel": "47", "inf": 1017}, {"prev_channel": "37", "inf": 825}]}, {"channel": 35, "count": 217, "layer": "mixed5b", "pagerank": 0.0011638974880627958, "prev_channels": [{"prev_channel": 806, "inf": 901}, {"prev_channel": 239, "inf": 1139}, {"prev_channel": 155, "inf": 83}], "attr_channels": [{"prev_channel": "239", "inf": 1139}, {"prev_channel": "806", "inf": 901}, {"prev_channel": "131", "inf": 736}]}, {"channel": 183, "count": 216, "layer": "mixed5b", "pagerank": 0.0011597115370302366, "prev_channels": [{"prev_channel": 806, "inf": 1136}, {"prev_channel": 239, "inf": 578}, {"prev_channel": 155, "inf": 1042}], "attr_channels": [{"prev_channel": "806", "inf": 1136}, {"prev_channel": "155", "inf": 1042}, {"prev_channel": "710", "inf": 853}]}, {"channel": 370, "count": 121, "layer": "mixed5b", "pagerank": 0.0006629710551845804, "prev_channels": [{"prev_channel": 239, "inf": 126}, {"prev_channel": 155, "inf": 442}], "attr_channels": [{"prev_channel": "742", "inf": 816}, {"prev_channel": "192", "inf": 668}, {"prev_channel": "87", "inf": 647}]}, {"channel": 198, "count": 142, "layer": "mixed5b", "pagerank": 0.0007718053532156356, "prev_channels": [], "attr_channels": [{"prev_channel": "247", "inf": 982}, {"prev_channel": "34", "inf": 835}, {"prev_channel": "58", "inf": 828}]}], "mixed5a": [{"channel": 388, "count": 553, "layer": "mixed5a", "pagerank": 0.0030126322502510524, "prev_channels": [{"prev_channel": 375, "inf": 1127}, {"prev_channel": 742, "inf": 838}, {"prev_channel": 726, "inf": 617}, {"prev_channel": 700, "inf": 615}, {"prev_channel": 788, "inf": 343}], "attr_channels": [{"prev_channel": "87", "inf": 1154}, {"prev_channel": "35", "inf": 944}, {"prev_channel": "28", "inf": 844}]}, {"channel": 806, "count": 236, "layer": "mixed5a", "pagerank": 0.0030172683347986524, "prev_channels": [{"prev_channel": 788, "inf": 1146}, {"prev_channel": 700, "inf": 217}], "attr_channels": [{"prev_channel": "788", "inf": 1146}, {"prev_channel": "117", "inf": 965}, {"prev_channel": "145", "inf": 704}]}, {"channel": 754, "count": 458, "layer": "mixed5a", "pagerank": 0.003437086509443333, "prev_channels": [{"prev_channel": 375, "inf": 1152}, {"prev_channel": 700, "inf": 603}, {"prev_channel": 742, "inf": 966}, {"prev_channel": 788, "inf": 5}, {"prev_channel": 726, "inf": 2}], "attr_channels": [{"prev_channel": "375", "inf": 1152}, {"prev_channel": "742", "inf": 966}, {"prev_channel": "89", "inf": 697}]}, {"channel": 239, "count": 217, "layer": "mixed5a", "pagerank": 0.002643879027100929, "prev_channels": [{"prev_channel": 726, "inf": 1299}, {"prev_channel": 700, "inf": 749}], "attr_channels": [{"prev_channel": "726", "inf": 1299}, {"prev_channel": "89", "inf": 1164}, {"prev_channel": "23", "inf": 930}]}, {"channel": 155, "count": 239, "layer": "mixed5a", "pagerank": 0.002623062243469515, "prev_channels": [{"prev_channel": 726, "inf": 1288}, {"prev_channel": 700, "inf": 859}, {"prev_channel": 375, "inf": 18}], "attr_channels": [{"prev_channel": "726", "inf": 1288}, {"prev_channel": "89", "inf": 1152}, {"prev_channel": "23", "inf": 934}]}], "mixed4e": [{"channel": 742, "count": 325, "layer": "mixed4e", "pagerank": 0.0015338981704233969, "prev_channels": [{"prev_channel": 457, "inf": 1104}, {"prev_channel": 322, "inf": 864}, {"prev_channel": 416, "inf": 93}], "attr_channels": [{"prev_channel": "457", "inf": 1104}, {"prev_channel": "70", "inf": 1092}, {"prev_channel": "512", "inf": 1034}]}, {"channel": 788, "count": 440, "layer": "mixed4e", "pagerank": 0.0018609241568682245, "prev_channels": [{"prev_channel": 416, "inf": 851}], "attr_channels": [{"prev_channel": "56", "inf": 1206}, {"prev_channel": "326", "inf": 1006}, {"prev_channel": "460", "inf": 852}]}, {"channel": 726, "count": 519, "layer": "mixed4e", "pagerank": 0.0019780720077199614, "prev_channels": [{"prev_channel": 416, "inf": 1107}, {"prev_channel": 37, "inf": 1294}, {"prev_channel": 457, "inf": 86}], "attr_channels": [{"prev_channel": "37", "inf": 1294}, {"prev_channel": "416", "inf": 1107}, {"prev_channel": "326", "inf": 1096}]}, {"channel": 375, "count": 311, "layer": "mixed4e", "pagerank": 0.0013235328673831335, "prev_channels": [{"prev_channel": 37, "inf": 600}, {"prev_channel": 416, "inf": 565}, {"prev_channel": 151, "inf": 544}, {"prev_channel": 457, "inf": 518}], "attr_channels": [{"prev_channel": "19", "inf": 1300}, {"prev_channel": "16", "inf": 1296}, {"prev_channel": "114", "inf": 1261}]}, {"channel": 700, "count": 816, "layer": "mixed4e", "pagerank": 0.0022330845673648385, "prev_channels": [{"prev_channel": 463, "inf": 1246}, {"prev_channel": 416, "inf": 1064}, {"prev_channel": 457, "inf": 447}, {"prev_channel": 322, "inf": 427}, {"prev_channel": 151, "inf": 391}], "attr_channels": [{"prev_channel": "30", "inf": 1300}, {"prev_channel": "16", "inf": 1286}, {"prev_channel": "2", "inf": 1242}]}], "mixed4d": [{"channel": 416, "count": 699, "layer": "mixed4d", "pagerank": 0.002451014252700134, "prev_channels": [{"prev_channel": 375, "inf": 1176}, {"prev_channel": 39, "inf": 856}, {"prev_channel": 424, "inf": 842}], "attr_channels": [{"prev_channel": "29", "inf": 1300}, {"prev_channel": "26", "inf": 1299}, {"prev_channel": "7", "inf": 1297}]}, {"channel": 37, "count": 407, "layer": "mixed4d", "pagerank": 0.0012458134078265047, "prev_channels": [], "attr_channels": [{"prev_channel": "122", "inf": 1297}, {"prev_channel": "75", "inf": 1191}, {"prev_channel": "102", "inf": 1070}]}, {"channel": 457, "count": 132, "layer": "mixed4d", "pagerank": 0.0008905893990861626, "prev_channels": [{"prev_channel": 375, "inf": 1293}, {"prev_channel": 424, "inf": 1113}, {"prev_channel": 77, "inf": 773}], "attr_channels": [{"prev_channel": "29", "inf": 1299}, {"prev_channel": "18", "inf": 1298}, {"prev_channel": "5", "inf": 1297}]}, {"channel": 322, "count": 177, "layer": "mixed4d", "pagerank": 0.0007564955726902799, "prev_channels": [{"prev_channel": 39, "inf": 1211}, {"prev_channel": 77, "inf": 1094}, {"prev_channel": 424, "inf": 466}, {"prev_channel": 375, "inf": 395}], "attr_channels": [{"prev_channel": "89", "inf": 1211}, {"prev_channel": "84", "inf": 836}, {"prev_channel": "128", "inf": 723}]}, {"channel": 82, "count": 268, "layer": "mixed4d", "pagerank": 0.0009556218681425996, "prev_channels": [], "attr_channels": [{"prev_channel": "121", "inf": 1293}, {"prev_channel": "69", "inf": 1235}, {"prev_channel": "43", "inf": 845}]}, {"channel": 151, "count": 122, "layer": "mixed4d", "pagerank": 0.0008186651736689545, "prev_channels": [{"prev_channel": 375, "inf": 787}, {"prev_channel": 424, "inf": 486}], "attr_channels": [{"prev_channel": "64", "inf": 1233}, {"prev_channel": "55", "inf": 1015}, {"prev_channel": "95", "inf": 710}]}, {"channel": 463, "count": 75, "layer": "mixed4d", "pagerank": 0.000772548102530318, "prev_channels": [{"prev_channel": 375, "inf": 1299}, {"prev_channel": 77, "inf": 1108}, {"prev_channel": 39, "inf": 257}, {"prev_channel": 424, "inf": 218}], "attr_channels": [{"prev_channel": "21", "inf": 1299}, {"prev_channel": "17", "inf": 1298}, {"prev_channel": "5", "inf": 1253}]}], "mixed4c": [{"channel": 487, "count": 536, "layer": "mixed4c", "pagerank": 0.002169015789943304, "prev_channels": [], "attr_channels": [{"prev_channel": "496", "inf": 1054}, {"prev_channel": "6", "inf": 964}, {"prev_channel": "127", "inf": 781}]}, {"channel": 375, "count": 602, "layer": "mixed4c", "pagerank": 0.002329206015761851, "prev_channels": [{"prev_channel": 407, "inf": 1286}, {"prev_channel": 442, "inf": 1250}, {"prev_channel": 447, "inf": 1111}, {"prev_channel": 402, "inf": 796}, {"prev_channel": 416, "inf": 673}], "attr_channels": [{"prev_channel": "111", "inf": 1300}, {"prev_channel": "124", "inf": 1167}, {"prev_channel": "52", "inf": 674}]}, {"channel": 77, "count": 330, "layer": "mixed4c", "pagerank": 0.0013360229886024877, "prev_channels": [{"prev_channel": 402, "inf": 291}, {"prev_channel": 442, "inf": 50}, {"prev_channel": 407, "inf": 52}], "attr_channels": [{"prev_channel": "4", "inf": 1178}, {"prev_channel": "128", "inf": 957}, {"prev_channel": "101", "inf": 888}]}, {"channel": 424, "count": 273, "layer": "mixed4c", "pagerank": 0.0010989618943092795, "prev_channels": [{"prev_channel": 407, "inf": 1162}, {"prev_channel": 416, "inf": 757}, {"prev_channel": 226, "inf": 445}, {"prev_channel": 271, "inf": 436}, {"prev_channel": 442, "inf": 217}, {"prev_channel": 402, "inf": 217}], "attr_channels": [{"prev_channel": "7", "inf": 1268}, {"prev_channel": "19", "inf": 1230}, {"prev_channel": "15", "inf": 946}]}, {"channel": 39, "count": 434, "layer": "mixed4c", "pagerank": 0.0014765972037012385, "prev_channels": [{"prev_channel": 226, "inf": 603}, {"prev_channel": 271, "inf": 104}], "attr_channels": [{"prev_channel": "17", "inf": 1298}, {"prev_channel": "96", "inf": 1235}, {"prev_channel": "299", "inf": 857}]}], "mixed4b": [{"channel": 407, "count": 272, "layer": "mixed4b", "pagerank": 0.0017492584668447565, "prev_channels": [{"prev_channel": 208, "inf": 1300}, {"prev_channel": 436, "inf": 654}, {"prev_channel": 437, "inf": 567}, {"prev_channel": 424, "inf": 359}], "attr_channels": [{"prev_channel": "17", "inf": 1300}, {"prev_channel": "23", "inf": 1020}, {"prev_channel": "16", "inf": 935}]}, {"channel": 447, "count": 244, "layer": "mixed4b", "pagerank": 0.0013675001478115523, "prev_channels": [{"prev_channel": 208, "inf": 1300}, {"prev_channel": 424, "inf": 410}, {"prev_channel": 437, "inf": 317}, {"prev_channel": 436, "inf": 195}], "attr_channels": [{"prev_channel": "17", "inf": 1300}, {"prev_channel": "3", "inf": 1257}, {"prev_channel": "16", "inf": 1176}]}, {"channel": 226, "count": 433, "layer": "mixed4b", "pagerank": 0.0017632494351676976, "prev_channels": [{"prev_channel": 208, "inf": 455}], "attr_channels": [{"prev_channel": "9", "inf": 1299}, {"prev_channel": "57", "inf": 1110}, {"prev_channel": "86", "inf": 599}]}, {"channel": 442, "count": 245, "layer": "mixed4b", "pagerank": 0.0013199999337514493, "prev_channels": [{"prev_channel": 208, "inf": 1293}, {"prev_channel": 437, "inf": 210}], "attr_channels": [{"prev_channel": "17", "inf": 1293}, {"prev_channel": "16", "inf": 1190}, {"prev_channel": "23", "inf": 1164}]}, {"channel": 271, "count": 390, "layer": "mixed4b", "pagerank": 0.001555280687969492, "prev_channels": [{"prev_channel": 424, "inf": 740}, {"prev_channel": 436, "inf": 582}, {"prev_channel": 437, "inf": 498}, {"prev_channel": 208, "inf": 387}], "attr_channels": [{"prev_channel": "89", "inf": 1036}, {"prev_channel": "12", "inf": 949}, {"prev_channel": "84", "inf": 911}]}, {"channel": 402, "count": 263, "layer": "mixed4b", "pagerank": 0.0015618467165138803, "prev_channels": [{"prev_channel": 208, "inf": 1300}, {"prev_channel": 424, "inf": 207}], "attr_channels": [{"prev_channel": "17", "inf": 1300}, {"prev_channel": "16", "inf": 1285}, {"prev_channel": "23", "inf": 1285}]}, {"channel": 416, "count": 257, "layer": "mixed4b", "pagerank": 0.0013035004345500506, "prev_channels": [{"prev_channel": 424, "inf": 395}, {"prev_channel": 437, "inf": 317}, {"prev_channel": 208, "inf": 286}], "attr_channels": [{"prev_channel": "16", "inf": 1300}, {"prev_channel": "2", "inf": 1289}, {"prev_channel": "21", "inf": 1258}]}], "mixed4a": [{"channel": 140, "count": 258, "layer": "mixed4a", "pagerank": 0.0017267311426018605, "prev_channels": [], "attr_channels": [{"prev_channel": "204", "inf": 1300}, {"prev_channel": "412", "inf": 1300}, {"prev_channel": "390", "inf": 1300}]}, {"channel": 208, "count": 642, "layer": "mixed4a", "pagerank": 0.0024062922258322713, "prev_channels": [{"prev_channel": 214, "inf": 1216}, {"prev_channel": 388, "inf": 1037}, {"prev_channel": 342, "inf": 1037}, {"prev_channel": 330, "inf": 415}, {"prev_channel": 340, "inf": 415}], "attr_channels": [{"prev_channel": "57", "inf": 1299}, {"prev_channel": "34", "inf": 1130}, {"prev_channel": "65", "inf": 1037}]}, {"channel": 424, "count": 432, "layer": "mixed4a", "pagerank": 0.0018125147468060622, "prev_channels": [{"prev_channel": 342, "inf": 714}, {"prev_channel": 388, "inf": 714}, {"prev_channel": 330, "inf": 266}, {"prev_channel": 340, "inf": 266}], "attr_channels": [{"prev_channel": "15", "inf": 1299}, {"prev_channel": "10", "inf": 1297}, {"prev_channel": "12", "inf": 1296}]}, {"channel": 436, "count": 437, "layer": "mixed4a", "pagerank": 0.0017125914383178255, "prev_channels": [{"prev_channel": 214, "inf": 1234}, {"prev_channel": 330, "inf": 1221}, {"prev_channel": 388, "inf": 1120}, {"prev_channel": 340, "inf": 673}, {"prev_channel": 342, "inf": 210}], "attr_channels": [{"prev_channel": "4", "inf": 1300}, {"prev_channel": "1", "inf": 1293}, {"prev_channel": "10", "inf": 1240}]}, {"channel": 437, "count": 414, "layer": "mixed4a", "pagerank": 0.001701679476447652, "prev_channels": [{"prev_channel": 214, "inf": 1234}, {"prev_channel": 388, "inf": 1100}, {"prev_channel": 330, "inf": 1100}, {"prev_channel": 342, "inf": 996}, {"prev_channel": 340, "inf": 886}], "attr_channels": [{"prev_channel": "7", "inf": 1300}, {"prev_channel": "1", "inf": 1249}, {"prev_channel": "15", "inf": 1231}]}], "mixed3b": [{"channel": 330, "count": 500, "layer": "mixed3b", "pagerank": 0.0018507594237662322, "prev_channels": [{"prev_channel": 69, "inf": 1105}, {"prev_channel": 134, "inf": 861}], "attr_channels": [{"prev_channel": "30", "inf": 1299}, {"prev_channel": "0", "inf": 1289}, {"prev_channel": "9", "inf": 1105}]}, {"channel": 342, "count": 431, "layer": "mixed3b", "pagerank": 0.0015603280158380136, "prev_channels": [{"prev_channel": 134, "inf": 1299}, {"prev_channel": 152, "inf": 1158}, {"prev_channel": 69, "inf": 1007}], "attr_channels": [{"prev_channel": "23", "inf": 1300}, {"prev_channel": "4", "inf": 1299}, {"prev_channel": "20", "inf": 1158}]}, {"channel": 214, "count": 142, "layer": "mixed3b", "pagerank": 0.0012862012112237668, "prev_channels": [{"prev_channel": 152, "inf": 1300}, {"prev_channel": 134, "inf": 1262}], "attr_channels": [{"prev_channel": "28", "inf": 1300}, {"prev_channel": "12", "inf": 1298}, {"prev_channel": "51", "inf": 1290}]}, {"channel": 340, "count": 555, "layer": "mixed3b", "pagerank": 0.0018484109512841948, "prev_channels": [{"prev_channel": 134, "inf": 1115}], "attr_channels": [{"prev_channel": "16", "inf": 1300}, {"prev_channel": "30", "inf": 1300}, {"prev_channel": "24", "inf": 1300}]}, {"channel": 388, "count": 597, "layer": "mixed3b", "pagerank": 0.0018178482743618199, "prev_channels": [{"prev_channel": 134, "inf": 1227}, {"prev_channel": 69, "inf": 874}], "attr_channels": [{"prev_channel": "26", "inf": 1300}, {"prev_channel": "7", "inf": 1240}, {"prev_channel": "8", "inf": 968}]}], "mixed3a": [{"channel": 69, "count": 366, "layer": "mixed3a", "pagerank": 0.001865254103989633, "prev_channels": [], "attr_channels": []}, {"channel": 134, "count": 354, "layer": "mixed3a", "pagerank": 0.0018967130323178517, "prev_channels": [], "attr_channels": []}, {"channel": 152, "count": 232, "layer": "mixed3a", "pagerank": 0.0017468221768449062, "prev_channels": [], "attr_channels": []}]}